drowsiness_validator/__init__.py
drowsiness_validator/api.py
drowsiness_validator/modules/__init__.py
drowsiness_validator/modules/validate.py
drowsiness_validator/modules/calculate/__init__.py
drowsiness_validator/modules/calculate/calculate.py
drowsiness_validator/modules/calculate/shape_predictor_68_face_landmarks.dat
drowsiness_validator/modules/predict/__init__.py
drowsiness_validator/modules/predict/cnn_model.py
drowsiness_validator/modules/predict/drowsiness_cnn_model.h5
drowsiness_validator/modules/predict/predict.py
drowsiness_validator-0.1.7.dist-info/METADATA
drowsiness_validator-0.1.7.dist-info/WHEEL
drowsiness_validator-0.1.7.dist-info/top_level.txt
drowsiness_validator-0.1.7.dist-info/RECORD
